p99Bluesky/__init__.py
p99Bluesky/__main__.py
p99Bluesky/_version.py
p99Bluesky-2.dist-info/LICENSE
p99Bluesky-2.dist-info/METADATA
p99Bluesky-2.dist-info/WHEEL
p99Bluesky-2.dist-info/entry_points.txt
p99Bluesky-2.dist-info/top_level.txt
p99Bluesky-2.dist-info/RECORD
